letnums.py
letnums-0.0.2.dist-info/METADATA
letnums-0.0.2.dist-info/WHEEL
letnums-0.0.2.dist-info/RECORD
