Metadata-Version: 2.1
Name: letnums
Version: 0.0.2
Summary: a simple library to generate random combinations of letters and numbers
Home-page: https://github.com/sokisa/letnum
Author: Sokisa
Requires-Python: >=3.11.1,<4.0.0
Classifier: Intended Audience :: Developers
Classifier: License :: OSI Approved :: MIT License
Classifier: Operating System :: OS Independent
Classifier: Programming Language :: Python :: 3
Classifier: Programming Language :: Python :: 3
Classifier: Topic :: Software Development :: Libraries
Requires-Dist: pika (>=0.0.1,<0.0.2)
Project-URL: Repository, https://github.com/sokisa/letnum
